{"is_source_file": true, "format": "JavaScript", "description": "This file defines a React custom hook called useNotes, which manages a collection of notes with features such as creation, updating, deletion, undo delete, pinning, persistence (loading and saving to storage), and ordering. It handles internal state management and side effects related to notes in a note-taking application.", "external_files": ["../utils/storage", "../utils/id", "../utils/time"], "external_methods": ["loadNotes", "saveNotes", "migrateIfNeeded", "uuid", "now"], "published": ["useNotes"], "classes": [], "methods": [{"name": "useNotes()", "description": "Main hook managing notes, providing functions to create, update, delete, undo delete, pin, unpin, and force save notes. It also exposes internal state properties such as the notes collection, order, and last opened note.", "scope": "", "scopeKind": ""}], "calls": ["react.useCallback", "react.useEffect", "react.useMemo", "react.useRef", "react.useState", "loadNotes", "saveNotes", "migrateIfNeeded", "uuid", "now"], "search-terms": ["useNotes React hook", "notes persistence", "notes collection management", "undo delete", "pinning notes", "notes ordering"], "state": 2, "file_id": 22, "knowledge_revision": 46, "git_revision": "", "ctags": [{"_type": "tag", "name": "VERSION", "path": "/home/kavia/workspace/code-generation/simple-notes-application-45998-46068/notes_frontend/src/hooks/useNotes.js", "pattern": "/^const VERSION = 1;$/", "language": "JavaScript", "kind": "constant"}, {"_type": "tag", "name": "useNotes", "path": "/home/kavia/workspace/code-generation/simple-notes-application-45998-46068/notes_frontend/src/hooks/useNotes.js", "pattern": "/^export function useNotes() {$/", "language": "JavaScript", "kind": "function", "signature": "()"}], "hash": "c16ecd247418d19d542e4f25ee4bad8f", "format-version": 4, "code-base-name": "notes_frontend", "filename": "notes_frontend/src/hooks/useNotes.js", "revision_history": [{"46": ""}]}